AUTHORS
ChangeLog
HACKING.rst
LICENSE
MANIFEST.in
README.rst
requirements.txt
setup.cfg
setup.py
test-requirements.txt
tox.ini
oslo/__init__.py
oslo.sphinx.egg-info/PKG-INFO
oslo.sphinx.egg-info/SOURCES.txt
oslo.sphinx.egg-info/dependency_links.txt
oslo.sphinx.egg-info/namespace_packages.txt
oslo.sphinx.egg-info/not-zip-safe
oslo.sphinx.egg-info/top_level.txt
oslo/sphinx/__init__.py
oslo/sphinx/intersphinx.py
oslo/sphinx/theme/openstack/layout.html
oslo/sphinx/theme/openstack/theme.conf
oslo/sphinx/theme/openstack/static/basic.css
oslo/sphinx/theme/openstack/static/default.css
oslo/sphinx/theme/openstack/static/header-line.gif
oslo/sphinx/theme/openstack/static/header_bg.jpg
oslo/sphinx/theme/openstack/static/nature.css
oslo/sphinx/theme/openstack/static/openstack_logo.png
oslo/sphinx/theme/openstack/static/tweaks.css